{
    "MoveToGoal": {
        "checkpoints": [
            {
                "steps": 47999968,
                "file_path": "results\\demo_Brain1\\MoveToGoal\\MoveToGoal-47999968.onnx",
                "reward": -3.923332691192627,
                "creation_time": 1668595415.40096,
                "auxillary_file_paths": [
                    "results\\demo_Brain1\\MoveToGoal\\MoveToGoal-47999968.pt"
                ]
            },
            {
                "steps": 48999900,
                "file_path": "results\\demo_Brain1\\MoveToGoal\\MoveToGoal-48999900.onnx",
                "reward": 0.4600004355112712,
                "creation_time": 1668596012.0004425,
                "auxillary_file_paths": [
                    "results\\demo_Brain1\\MoveToGoal\\MoveToGoal-48999900.pt"
                ]
            },
            {
                "steps": 49999803,
                "file_path": "results\\demo_Brain1\\MoveToGoal\\MoveToGoal-49999803.onnx",
                "reward": -2.651999521255493,
                "creation_time": 1668596609.604354,
                "auxillary_file_paths": [
                    "results\\demo_Brain1\\MoveToGoal\\MoveToGoal-49999803.pt"
                ]
            },
            {
                "steps": 50999990,
                "file_path": "results\\demo_Brain1\\MoveToGoal\\MoveToGoal-50999990.onnx",
                "reward": -3.345999574661255,
                "creation_time": 1668597212.348982,
                "auxillary_file_paths": [
                    "results\\demo_Brain1\\MoveToGoal\\MoveToGoal-50999990.pt"
                ]
            },
            {
                "steps": 51999922,
                "file_path": "results\\demo_Brain1\\MoveToGoal\\MoveToGoal-51999922.onnx",
                "reward": -9.996665954589844,
                "creation_time": 1668597831.5189474,
                "auxillary_file_paths": [
                    "results\\demo_Brain1\\MoveToGoal\\MoveToGoal-51999922.pt"
                ]
            },
            {
                "steps": 52999812,
                "file_path": "results\\demo_Brain1\\MoveToGoal\\MoveToGoal-52999812.onnx",
                "reward": -2.8519994258880614,
                "creation_time": 1668598439.4919705,
                "auxillary_file_paths": [
                    "results\\demo_Brain1\\MoveToGoal\\MoveToGoal-52999812.pt"
                ]
            },
            {
                "steps": 53999973,
                "file_path": "results\\demo_Brain1\\MoveToGoal\\MoveToGoal-53999973.onnx",
                "reward": -9.99599928855896,
                "creation_time": 1668599064.3326354,
                "auxillary_file_paths": [
                    "results\\demo_Brain1\\MoveToGoal\\MoveToGoal-53999973.pt"
                ]
            },
            {
                "steps": 54999985,
                "file_path": "results\\demo_Brain1\\MoveToGoal\\MoveToGoal-54999985.onnx",
                "reward": -3.386666218439738,
                "creation_time": 1668599698.6925862,
                "auxillary_file_paths": [
                    "results\\demo_Brain1\\MoveToGoal\\MoveToGoal-54999985.pt"
                ]
            },
            {
                "steps": 55999884,
                "file_path": "results\\demo_Brain1\\MoveToGoal\\MoveToGoal-55999884.onnx",
                "reward": -0.8099995851516724,
                "creation_time": 1668600339.282333,
                "auxillary_file_paths": [
                    "results\\demo_Brain1\\MoveToGoal\\MoveToGoal-55999884.pt"
                ]
            },
            {
                "steps": 56999775,
                "file_path": "results\\demo_Brain1\\MoveToGoal\\MoveToGoal-56999775.onnx",
                "reward": -5.354999542236328,
                "creation_time": 1668600953.0320678,
                "auxillary_file_paths": [
                    "results\\demo_Brain1\\MoveToGoal\\MoveToGoal-56999775.pt"
                ]
            },
            {
                "steps": 57999789,
                "file_path": "results\\demo_Brain1\\MoveToGoal\\MoveToGoal-57999789.onnx",
                "reward": -9.998332619667053,
                "creation_time": 1668601584.5719755,
                "auxillary_file_paths": [
                    "results\\demo_Brain1\\MoveToGoal\\MoveToGoal-57999789.pt"
                ]
            },
            {
                "steps": 58999956,
                "file_path": "results\\demo_Brain1\\MoveToGoal\\MoveToGoal-58999956.onnx",
                "reward": -9.997999286651611,
                "creation_time": 1668602220.363593,
                "auxillary_file_paths": [
                    "results\\demo_Brain1\\MoveToGoal\\MoveToGoal-58999956.pt"
                ]
            },
            {
                "steps": 59999844,
                "file_path": "results\\demo_Brain1\\MoveToGoal\\MoveToGoal-59999844.onnx",
                "reward": -9.999999284744263,
                "creation_time": 1668602854.297823,
                "auxillary_file_paths": [
                    "results\\demo_Brain1\\MoveToGoal\\MoveToGoal-59999844.pt"
                ]
            },
            {
                "steps": 60999828,
                "file_path": "results\\demo_Brain1\\MoveToGoal\\MoveToGoal-60999828.onnx",
                "reward": -3.856666088104248,
                "creation_time": 1668603477.667609,
                "auxillary_file_paths": [
                    "results\\demo_Brain1\\MoveToGoal\\MoveToGoal-60999828.pt"
                ]
            },
            {
                "steps": 61953886,
                "file_path": "results\\demo_Brain1\\MoveToGoal\\MoveToGoal-61953886.onnx",
                "reward": null,
                "creation_time": 1668604071.4003775,
                "auxillary_file_paths": [
                    "results\\demo_Brain1\\MoveToGoal\\MoveToGoal-61953886.pt"
                ]
            }
        ]
    },
    "metadata": {
        "stats_format_version": "0.3.0",
        "mlagents_version": "0.28.0",
        "torch_version": "1.7.1+cpu"
    }
}